{
    "$id": "rect",
    "examples": [
        {
            "x": 0,
            "y": 0,
            "width": 1,
            "height": 0.3
        }
    ],
    "type": "object",
    "properties": {
        "x": {
            "type": "number"
        },
        "y": {
            "type": "number"
        },
        "width": {
            "type": "number"
        },
        "height": {
            "type": "number"
        }
    },
    "required": [
        "x",
        "y",
        "width",
        "height"
    ]
}